esil/__init__.py
esil/date_helper.py
esil/earth_helper.py
esil/file_helper.py
esil/interpolation_helper.py
esil/log_helper.py
esil/map_helper.py
esil/monitor_helper.py
esil/netcdf_helper.py
esil/panelayout_helper.py
esil/plot_helper.py
esil/projection_helper.py
esil/regrid_helper.py
esil/scatter_plot_helper.py
esil/sqlite_helper.py
esil/wrf_helper.py
esil/rsm_helper/__init__.py
esil/rsm_helper/count_code_lines.py
esil/rsm_helper/ekma_curve.py
esil/rsm_helper/factor.py
esil/rsm_helper/get_differentiate.py
esil/rsm_helper/grid_file.py
esil/rsm_helper/model_property.py
esil/rsm_helper/rsm_worker.py
esil-1.3.5.dist-info/LICENSE
esil-1.3.5.dist-info/METADATA
esil-1.3.5.dist-info/WHEEL
esil-1.3.5.dist-info/top_level.txt
esil-1.3.5.dist-info/RECORD
