Metadata-Version: 2.2
Name: esil
Version: 1.3.5
Summary: commonly used functions written by Devin Long
Home-page: https://github.com/Devin-Long-7/esil
Author: Devin Long
Author-email: long.sc@qq.com
Classifier: Programming Language :: Python :: 3
Classifier: License :: OSI Approved :: MIT License
Classifier: Operating System :: OS Independent
Requires-Python: >=3.7
License-File: LICENSE
Requires-Dist: numpy
Requires-Dist: pandas
Requires-Dist: xarray
Requires-Dist: scipy
Requires-Dist: tqdm
Requires-Dist: netCDF4
Requires-Dist: pyproj
Requires-Dist: SQLAlchemy
Requires-Dist: chardet
Requires-Dist: sympy
Requires-Dist: shapely
Requires-Dist: pytz
Requires-Dist: cartopy
Requires-Dist: geopandas
Dynamic: author
Dynamic: author-email
Dynamic: classifier
Dynamic: description
Dynamic: description-content-type
Dynamic: home-page
Dynamic: requires-dist
Dynamic: requires-python
Dynamic: summary
